pytunes/__init__.py
pytunes/client.py
pytunes/constants.py
pytunes/daemon.py
pytunes/database.py
pytunes/itc.py
pytunes/playlist.py
pytunes/playlist_export_parser.py
pytunes/status.py
pytunes/terminology.py
pytunes-13.0.2.dist-info/METADATA
pytunes-13.0.2.dist-info/WHEEL
pytunes-13.0.2.dist-info/entry_points.txt
pytunes-13.0.2.dist-info/top_level.txt
pytunes-13.0.2.dist-info/RECORD
